.gitignore
LICENSE
README.md
demo.py
pyproject.toml
screenshot.jpg
screenshot2.jpg
screenshot_multicam.jpg
.github/workflows/python-publish.yml
docs/Makefile
docs/abbrev_long.bib
docs/conf.py
docs/conf_overrides.py
docs/conf_spec.py
docs/index.rst
docs/make.bat
docs/references.bib
docs/_static/styles/my_theme.css
docs/_templates/autoapi/index.rst
docs/_templates/autoapi/python/attribute.rst
docs/_templates/autoapi/python/class.rst
docs/_templates/autoapi/python/data.rst
docs/_templates/autoapi/python/exception.rst
docs/_templates/autoapi/python/function.rst
docs/_templates/autoapi/python/method.rst
docs/_templates/autoapi/python/module.rst
docs/_templates/autoapi/python/package.rst
docs/_templates/autoapi/python/property.rst
docs_old/API.md
docs_old/index.md
docs_old/poseviz.md
docs_old/stylesheets/extra.css
src/poseviz/__init__.py
src/poseviz/colors.py
src/poseviz/draw2d.py
src/poseviz/init.py
src/poseviz/mayavi_util.py
src/poseviz/messages.py
src/poseviz/poseviz.py
src/poseviz/video_writing.py
src/poseviz/view_info.py
src/poseviz.egg-info/PKG-INFO
src/poseviz.egg-info/SOURCES.txt
src/poseviz.egg-info/dependency_links.txt
src/poseviz.egg-info/requires.txt
src/poseviz.egg-info/top_level.txt
src/poseviz/components/__init__.py
src/poseviz/components/camera_viz.py
src/poseviz/components/connected_points_viz.py
src/poseviz/components/ground_plane_viz.py
src/poseviz/components/main_viz.py
src/poseviz/components/skeletons_viz.py
src/poseviz/components/smpl_viz.py