Metadata-Version: 2.4
Name: poseviz
Version: 0.0.0
Summary: 3D human pose visualizer with multi-person, multi-view support, built on Mayavi.
Author-email: István Sárándi <istvan.sarandi@uni-tuebingen.de>
License: MIT License
Requires-Python: >=3.8
License-File: LICENSE
Requires-Dist: more-itertools
Requires-Dist: opencv-python
Requires-Dist: numpy
Requires-Dist: mayavi
Requires-Dist: imageio
Requires-Dist: cameravision
Requires-Dist: boxlib
Requires-Dist: framepump
Dynamic: license-file
